setup.py
materialModels/__init__.py
materialModels.egg-info/PKG-INFO
materialModels.egg-info/SOURCES.txt
materialModels.egg-info/dependency_links.txt
materialModels.egg-info/requires.txt
materialModels.egg-info/top_level.txt
materialModels.egg-info/zip-safe
materialModels/componentReference/__init__.py
materialModels/fvPatchFields/__init__.py
materialModels/fvPatchFields/tractionDisplacement/__init__.py
materialModels/rheologyModel/__init__.py
materialModels/rheologyModel/rheologyLaws/__init__.py
materialModels/rheologyModel/rheologyLaws/addDictionaryConstructorTable.py
materialModels/rheologyModel/rheologyLaws/linearElastic.py
materialModels/rheologyModel/rheologyLaws/multiMaterial.py
materialModels/rheologyModel/rheologyLaws/rheologyLaw.py